imbi/__init__.py
imbi/app.py
imbi/auth.py
imbi/base.py
imbi/common.py
imbi/html.py
imbi/ldap.py
imbi/pkgfiles.py
imbi/session.py
imbi/timestamp.py
imbi/uimodules.py
imbi/user.py
imbi/views/__init__.py
imbi/views/error.py
imbi/views/home.py
imbi/views/operations/__init__.py
imbi/views/operations/changelog.py
imbi/views/services/__init__.py
imbi/views/services/graph.py
imbi/views/services/inventory.py
imbi-0.1.0.dist-info/LICENSE
imbi-0.1.0.dist-info/METADATA
imbi-0.1.0.dist-info/WHEEL
imbi-0.1.0.dist-info/entry_points.txt
imbi-0.1.0.dist-info/top_level.txt
imbi-0.1.0.dist-info/RECORD
