Metadata-Version: 2.1
Name: imbi
Version: 0.1.0
Summary: Imbi Service Management System
Home-page: https://github.aweber.io/PSE/Applications/imbi
Author: AWeber Communications, Inc.
Author-email: api@aweber.com
License: UNKNOWN
Platform: UNKNOWN
Classifier: Development Status :: 3 - Alpha
Classifier: Intended Audience :: Developers
Classifier: License :: Other/Proprietary License
Classifier: Natural Language :: English
Classifier: Operating System :: OS Independent
Classifier: Programming Language :: Python :: 3
Classifier: Programming Language :: Python :: 3.7
Requires-Dist: aioredis (==1.2.0)
Requires-Dist: arrow (==0.10.0)
Requires-Dist: jsonpatch (==1.14)
Requires-Dist: jsonschema (==2.5.1)
Requires-Dist: ietfparse (==1.4.1)
Requires-Dist: ldap3 (<3,>=2.5)
Requires-Dist: pycurl (==7.43.0)
Requires-Dist: raven (<7,>=6.9.0)
Requires-Dist: tornado (==5.1.1)
Requires-Dist: u-msgpack-python (==2.1)
Requires-Dist: sprockets.handlers.status (==0.1.2)
Requires-Dist: sprockets.http (==2.0.0)
Requires-Dist: sprockets.mixins.correlation (==2.0.0)
Requires-Dist: sprockets.mixins.mediatype (==2.2.2)
